.gitignore
.pre-commit-config.yaml
LICENSE
MANIFEST.in
Makefile
README.md
install_tempo2.sh
pyproject.toml
setup.py
.github/workflows/ci_tests.yml
demo/libstempo-demo.ipynb
demo/libstempo-toasim-demo.ipynb
libstempo/.gitignore
libstempo/GWsim-stub.h
libstempo/__init__.py
libstempo/_find_tempo2.py
libstempo/_version.py
libstempo/eccUtils.py
libstempo/ecc_vs_nharm.txt
libstempo/emcee.py
libstempo/fit.py
libstempo/libstempo.cpp
libstempo/libstempo.pyx
libstempo/like.py
libstempo/multinest.py
libstempo/plot.py
libstempo/spharmORFbasis.py
libstempo/t2fit-stub.h
libstempo/toasim.py
libstempo/utils.py
libstempo.egg-info/PKG-INFO
libstempo.egg-info/SOURCES.txt
libstempo.egg-info/dependency_links.txt
libstempo.egg-info/requires.txt
libstempo.egg-info/top_level.txt
libstempo/data/B1953+29_NANOGrav_dfg+12.par
libstempo/data/B1953+29_NANOGrav_dfg+12.tim
libstempo/data/J1909-3744_NANOGrav_dfg+12.par
libstempo/data/J1909-3744_NANOGrav_dfg+12.tim
tests/test_fakepulsar.py
tests/test_imports.py
tests/test_pulsar.py