Metadata-Version: 2.4
Name: libstempo
Version: 2.5.1
Summary: A Python wrapper for tempo2
Author-email: Michele Vallisneri <vallis@vallis.org>
License: MIT
Project-URL: Homepage, https://github.com/vallis/libstempo
Classifier: Intended Audience :: Developers
Classifier: Intended Audience :: Science/Research
Classifier: License :: OSI Approved :: MIT License
Classifier: Operating System :: MacOS
Classifier: Operating System :: POSIX :: Linux
Classifier: Programming Language :: Python :: 3
Classifier: Programming Language :: Python :: 3.8
Classifier: Programming Language :: Python :: 3.9
Classifier: Programming Language :: Python :: 3.10
Classifier: Programming Language :: Python :: 3.11
Classifier: Programming Language :: Python :: 3.12
Requires-Python: <4,>=3.8
License-File: LICENSE
Requires-Dist: numpy<2.0; python_version == "3.8"
Requires-Dist: numpy; python_version > "3.8"
Requires-Dist: scipy
Requires-Dist: matplotlib
Requires-Dist: ephem
Provides-Extra: astropy
Requires-Dist: astropy; extra == "astropy"
Provides-Extra: dev
Requires-Dist: black; extra == "dev"
Requires-Dist: flake8; extra == "dev"
Requires-Dist: Flake8-pyproject; extra == "dev"
Requires-Dist: pre-commit; extra == "dev"
Requires-Dist: wheel; extra == "dev"
Requires-Dist: coverage; extra == "dev"
Requires-Dist: pytest; extra == "dev"
Requires-Dist: pytest-cov; extra == "dev"
Requires-Dist: jupyter; extra == "dev"
Dynamic: license-file
